Metadata-Version: 2.1
Name: odoo14-addon-stock_picking_type_user_restriction
Version: 14.0.1.0.2
Summary: Restrict some users to see and use only certain picking types
Home-page: https://github.com/OCA/stock-logistics-warehouse
Author: Xtendoo, TAKOBI, Odoo Community Association (OCA)
Author-email: support@odoo-community.org
License: LGPL-3
Classifier: Programming Language :: Python
Classifier: Framework :: Odoo
Classifier: Framework :: Odoo :: 14.0
Classifier: License :: OSI Approved :: GNU Lesser General Public License v3 (LGPLv3)
Requires-Python: >=3.6
Requires-Dist: odoo<14.1dev,>=14.0a
Requires-Dist: openupgradelib
